synth_mapping_helper/__init__.py
synth_mapping_helper/analysis.py
synth_mapping_helper/audio_format.py
synth_mapping_helper/cli.py
synth_mapping_helper/companion.py
synth_mapping_helper/finalize.py
synth_mapping_helper/gui.py
synth_mapping_helper/movement.py
synth_mapping_helper/pattern_generation.py
synth_mapping_helper/rails.py
synth_mapping_helper/synth_format.py
synth_mapping_helper/utils.py
synth_mapping_helper/gui_tabs/__init__.py
synth_mapping_helper/gui_tabs/autobackup.py
synth_mapping_helper/gui_tabs/commands.py
synth_mapping_helper/gui_tabs/dashboard.py
synth_mapping_helper/gui_tabs/file_utils.py
synth_mapping_helper/gui_tabs/local_dir_picker.py
synth_mapping_helper/gui_tabs/map_render.py
synth_mapping_helper/gui_tabs/prevent_default_keyboard.js
synth_mapping_helper/gui_tabs/stacking.py
synth_mapping_helper/gui_tabs/text_gen.py
synth_mapping_helper/gui_tabs/utils.py
synth_mapping_helper/gui_tabs/version.py
synth_mapping_helper/gui_tabs/wall_art.py
synth_mapping_helper-1.5.19.dist-info/licenses/LICENSE
synth_mapping_helper-1.5.19.dist-info/METADATA
synth_mapping_helper-1.5.19.dist-info/WHEEL
synth_mapping_helper-1.5.19.dist-info/entry_points.txt
synth_mapping_helper-1.5.19.dist-info/top_level.txt
synth_mapping_helper-1.5.19.dist-info/RECORD
