Metadata-Version: 2.4
Name: synth_mapping_helper
Version: 1.5.19
Summary: Toolbox for manipulating the JSON-Format used by Synth Riders Beatmap Editor in the clipboard
Author: adosikas
License: MIT License
Project-URL: Homepage, https://github.com/adosikas/synth_mapping_helper
Project-URL: Documentation, https://github.com/adosikas/synth_mapping_helper/wiki
Project-URL: Repository, https://github.com/adosikas/synth_mapping_helper
Project-URL: Bug Tracker, https://github.com/adosikas/synth_mapping_helper/issues
Project-URL: Changelog, https://github.com/adosikas/synth_mapping_helper/releases
Classifier: Development Status :: 4 - Beta
Classifier: Intended Audience :: End Users/Desktop
Classifier: Topic :: Artistic Software
Classifier: Topic :: Games/Entertainment
Classifier: Programming Language :: Python :: 3
Classifier: Programming Language :: Python :: 3.11
Classifier: Programming Language :: Python :: 3.12
Classifier: Programming Language :: Python :: 3.13
Classifier: Programming Language :: Python :: 3 :: Only
Classifier: License :: OSI Approved :: MIT License
Classifier: Operating System :: OS Independent
Requires-Python: >=3.11
License-File: LICENSE
Requires-Dist: numpy==2.2.6
Requires-Dist: numba==0.61.2
Requires-Dist: scipy==1.16.2
Requires-Dist: matplotlib==3.10.6
Requires-Dist: plotly==6.3.0
Requires-Dist: pyperclip==1.9.0
Requires-Dist: watchdog==6.0.0
Requires-Dist: requests==2.32.5
Requires-Dist: nicegui==2.24.1
Requires-Dist: librosa==0.11.0
Requires-Dist: soundfile==0.13.1
Requires-Dist: audioread==3.0.1
Requires-Dist: pywin32==311; sys_platform == "win32"
Dynamic: license-file
